solar_radio_image_viewer/__init__.py
solar_radio_image_viewer/create_video.py
solar_radio_image_viewer/dialogs.py
solar_radio_image_viewer/helioprojective.py
solar_radio_image_viewer/helioprojective_viewer.py
solar_radio_image_viewer/helioviewer_browser.py
solar_radio_image_viewer/install_utils.py
solar_radio_image_viewer/log_console.py
solar_radio_image_viewer/main.py
solar_radio_image_viewer/move_phasecenter.py
solar_radio_image_viewer/norms.py
solar_radio_image_viewer/searchable_combobox.py
solar_radio_image_viewer/splash.py
solar_radio_image_viewer/styles.py
solar_radio_image_viewer/tutorial.py
solar_radio_image_viewer/utils.py
solar_radio_image_viewer/version.py
solar_radio_image_viewer/video_dialog.py
solar_radio_image_viewer/video_utils.py
solar_radio_image_viewer/viewer.py
solar_radio_image_viewer/assets/Inter-Bold.ttf
solar_radio_image_viewer/assets/Inter-Medium.ttf
solar_radio_image_viewer/assets/Inter-Regular.ttf
solar_radio_image_viewer/assets/Inter-SemiBold.ttf
solar_radio_image_viewer/assets/NotoEmoji-Regular.ttf
solar_radio_image_viewer/assets/__init__.py
solar_radio_image_viewer/assets/add_tab_default.png
solar_radio_image_viewer/assets/add_tab_default_light.png
solar_radio_image_viewer/assets/add_tab_hover.png
solar_radio_image_viewer/assets/add_tab_hover_light.png
solar_radio_image_viewer/assets/browse.png
solar_radio_image_viewer/assets/browse_light.png
solar_radio_image_viewer/assets/close_tab_default.png
solar_radio_image_viewer/assets/close_tab_default_light.png
solar_radio_image_viewer/assets/close_tab_hover.png
solar_radio_image_viewer/assets/close_tab_hover_light.png
solar_radio_image_viewer/assets/ellipse_selection.png
solar_radio_image_viewer/assets/ellipse_selection_light.png
solar_radio_image_viewer/assets/icon.png
solar_radio_image_viewer/assets/icons8-ellipse-90.png
solar_radio_image_viewer/assets/icons8-ellipse-90_light.png
solar_radio_image_viewer/assets/icons8-info-90.png
solar_radio_image_viewer/assets/icons8-info-90_light.png
solarviewer-1.2.4.dist-info/licenses/LICENSE
solarviewer-1.2.4.dist-info/METADATA
solarviewer-1.2.4.dist-info/WHEEL
solarviewer-1.2.4.dist-info/entry_points.txt
solarviewer-1.2.4.dist-info/top_level.txt
solarviewer-1.2.4.dist-info/RECORD
