Metadata-Version: 2.4
Name: solarviewer
Version: 1.2.4
Summary: SolarViewer - A comprehensive tool for visualizing and analyzing solar radio images
Home-page: https://github.com/dey-soham/solarviewer/
Author: Soham Dey
Author-email: sohamd943@gmail.com
License: MIT
Project-URL: Documentation, https://github.com/dey-soham/solarviewer/wiki
Project-URL: Source, https://github.com/dey-soham/solarviewer/
Project-URL: Tracker, https://github.com/dey-soham/solarviewer/issues
Classifier: Development Status :: 5 - Production/Stable
Classifier: Intended Audience :: Science/Research
Classifier: Topic :: Scientific/Engineering :: Astronomy
Classifier: Programming Language :: Python :: 3
Classifier: Programming Language :: Python :: 3.10
Classifier: Programming Language :: Python :: 3.11
Classifier: Programming Language :: Python :: 3.12
Classifier: Programming Language :: Python :: 3.13
Requires-Python: >=3.10
License-File: LICENSE
Requires-Dist: setuptools<81
Requires-Dist: PyQt5>=5.15.0
Requires-Dist: matplotlib>=3.5.0
Requires-Dist: numpy>=1.20.0
Requires-Dist: astropy>=5.0.0
Requires-Dist: scipy>=1.7.0
Requires-Dist: drms
Requires-Dist: casatools>=6.4.0
Requires-Dist: casatasks>=6.4.0
Requires-Dist: sunpy[image,map,net,timeseries,visualization]>=5.0.0
Requires-Dist: pillow
Requires-Dist: python-casacore
Requires-Dist: seaborn
Requires-Dist: opencv-python-headless
Requires-Dist: dask>=2022.1.0
Requires-Dist: zarr>=2.11.0
Requires-Dist: pyqt5-sip>=12.9.0
Requires-Dist: qtpy>=2.0.0
Requires-Dist: imageio>=2.16.0
Requires-Dist: tifffile>=2022.2.2
Requires-Dist: aiapy>=0.1.0
Requires-Dist: imageio[ffmpeg]
Requires-Dist: paramiko>=3.0.0
Dynamic: author
Dynamic: author-email
Dynamic: classifier
Dynamic: description
Dynamic: description-content-type
Dynamic: home-page
Dynamic: license
Dynamic: license-file
Dynamic: project-url
Dynamic: requires-dist
Dynamic: requires-python
Dynamic: summary
